accrete_feature_store/__init__.py
accrete_feature_store/__main__.py
accrete_feature_store/models/__init__.py
accrete_feature_store/models/v1/__init__.py
accrete_feature_store/models/v1/kepler/__init__.py
accrete_feature_store/models/v1/kepler/social_media_post_embedding.py
db/__init__.py
acc_feature_store_schema-0.1.dist-info/LICENCE
acc_feature_store_schema-0.1.dist-info/METADATA
acc_feature_store_schema-0.1.dist-info/WHEEL
acc_feature_store_schema-0.1.dist-info/entry_points.txt
acc_feature_store_schema-0.1.dist-info/top_level.txt
acc_feature_store_schema-0.1.dist-info/RECORD
