Metadata-Version: 2.1
Name: acc_feature_store_schema
Version: 0.1
Summary: operational workflows that enable defining and adding schemas to the database so that our data structure remains consistent and scalable as our machine learning needs grow.
Home-page: https://gitlab.com/accreteai-main/data-platform/feature-store/acc-feature-store-schemas
Author: Abhishek Pattnaik
Author-email: abhishek.pattnaik@accrete.ai
License: LICENSE.txt
Project-URL: Homepage, https://gitlab.com/accreteai-main/data-platform/feature-store/acc-feature-store-schemas
Project-URL: Source Code, https://gitlab.com/accreteai-main/data-platform/feature-store/acc-feature-store-schemas
Classifier: Environment :: Web Environment
Classifier: Intended Audience :: Developers
Classifier: License :: OSI Approved :: Apache Software License
Classifier: Operating System :: OS Independent
Classifier: Programming Language :: Python
Classifier: Programming Language :: Python :: 3
Classifier: Programming Language :: Python :: 3.10
Classifier: Programming Language :: Python :: 3.11
Requires-Python: ~=3.7
License-File: LICENCE
Provides-Extra: dev
Requires-Dist: mypy[reports] ; extra == 'dev'
Requires-Dist: pytest ; extra == 'dev'
Requires-Dist: pytest-cov ; extra == 'dev'
Requires-Dist: mypy ; extra == 'dev'
Requires-Dist: ruff ; extra == 'dev'
Requires-Dist: uv ; extra == 'dev'
Requires-Dist: pre-commit ; extra == 'dev'
Requires-Dist: build ; extra == 'dev'
Requires-Dist: angreal ; extra == 'dev'
